{
  "version": "7",
  "dialect": "sqlite",
  "entries": [
    {
      "idx": 0,
      "version": "6",
      "when": 1775192383623,
      "tag": "0000_sloppy_nextwave",
      "breakpoints": true
    },
    {
      "idx": 1,
      "version": "6",
      "when": 1775267852160,
      "tag": "0001_update_schema_jaspel_v2",
      "breakpoints": true
    },
    {
      "idx": 2,
      "version": "6",
      "when": 1775301782209,
      "tag": "0002_cheerful_king_cobra",
      "breakpoints": true
    },
    {
      "idx": 3,
      "version": "6",
      "when": 1776213455425,
      "tag": "0003_free_goblin_queen",
      "breakpoints": true
    }
  ]
}